{
  "name": "Van's RV-14A",
  "type": "single_engine",
  "engine_count": 1,
  "wing_area": 126.0,
  "aspect_ratio": 6.5,
  "CD0": 0.03,
  "e": 0.84,
  "configuration_options": {
    "flaps": [
      "clean",
      "takeoff",
      "landing"
    ]
  },
  "G_limits": {
    "normal": {
      "clean": {
        "positive": 3.8,
        "negative": -1.5
      },
      "takeoff": {
        "positive": 2.0,
        "negative": -1.0
      },
      "landing": {
        "positive": 2.0,
        "negative": -1.0
      }
    },
    "utility": {
      "clean": {
        "positive": 4.4,
        "negative": -1.5
      },
      "takeoff": {
        "positive": 2.0,
        "negative": -1.0
      },
      "landing": {
        "positive": 2.0,
        "negative": -1.0
      }
    },
    "aerobatic": {
      "clean": {
        "positive": 6.0,
        "negative": -1.5
      },
      "takeoff": {
        "positive": 0.0,
        "negative": 0.0
      },
      "landing": {
        "positive": 0.0,
        "negative": 0.0
      }
    }
  },
  "stall_speeds": {
    "clean": {
      "weights": [
        1800,
        1925,
        2050
      ],
      "speeds": [
        55,
        58,
        60
      ]
    },
    "takeoff": {
      "weights": [
        1800,
        1925,
        2050
      ],
      "speeds": [
        52,
        55,
        57
      ]
    },
    "landing": {
      "weights": [
        1800,
        1925,
        2050
      ],
      "speeds": [
        49,
        52,
        54
      ]
    }
  },
  "single_engine_limits": {
    "best_glide": 70,
    "best_glide_ratio": 9.0
  },
  "engine_options": {
    "Lycoming IO-390": {
      "horsepower": 210,
      "power_curve": {
        "sea_level_max": 210,
        "derate_per_1000ft": 0.03
      }
    }
  },
  "max_altitude": 18000,
  "Vne": 210,
  "Vno": 160,
  "Vfe": {
    "takeoff": 100,
    "landing": 87
  },
  "CL_max": {
    "clean": 1.5,
    "takeoff": 1.7,
    "landing": 1.9
  },
  "arcs": {
    "white": [
      49,
      87
    ],
    "green": [
      55,
      160
    ],
    "yellow": [
      160,
      210
    ],
    "red": 210
  },
  "empty_weight": 1275,
  "max_weight": 2050,
  "seats": 2,
  "cg_range": [
    86.01,
    94.01
  ],
  "fuel_capacity_gal": 50,
  "fuel_weight_per_gal": 6.0,
  "prop_thrust_decay": {
    "T_static_factor": 2.6,
    "V_max_kts": 210
  },
  "Vx": 75,
  "Vy": 95
}